phy/Generador128f.v
module Generador128f (
  input clk_8f,
  input reset,
  output reg clk_f,
  output reg clk_2f);

  reg [1:0] contador;
  reg [3:0] contador2;

  always @ (posedge clk_8f) begin
    if (reset == 0) begin
      contador <= 0;
      contador2 <= 0;
      clk_2f <= 0;
      clk_f <= 0;
    end else begin
      contador <= contador + 1;
      contador2 <= contador2 + 1;
      if (contador == 0 || contador == 2) begin
        clk_2f <= ~clk_2f;
      end else begin
        clk_2f <= clk_2f;
      end
      if (contador2 == 0 || contador2 == 4) begin
        clk_f <= ~clk_f;
        if (contador2 == 4) begin
          contador2 <= 1;
        end
      end else begin
        clk_f <= clk_f;
      end
    end
  end
endmodule //Generador12clk_8f

Desktop/phy_rx/phy_tx/ParaleloSerie/ParaleloSerie_Est.v
/* Generated by Yosys 0.7 (git sha1 61f6811, gcc 4.8.4-2ubuntu1~14.04.3 -O2 -fstack-protector -fPIC -Os) */

(* top =  1  *)
(* src = "ParaleloSerie_Est.v:1" *)
module ParaleloSerie_Est(data_inP, reset, clk_8f, clk_f, valid_in, data2send_est, data_outS_est);
  (* src = "ParaleloSerie_Est.v:13" *)
  wire [2:0] _000_;
  (* src = "ParaleloSerie_Est.v:18" *)
  wire [7:0] _001_;
  wire _002_;
  wire _003_;
  wire _004_;
  wire _005_;
  wire _006_;
  wire _007_;
  wire _008_;
  wire _009_;
  wire _010_;
  wire _011_;
  wire _012_;
  wire _013_;
  wire _014_;
  wire _015_;
  wire _016_;
  wire _017_;
  wire _018_;
  wire _019_;
  wire _020_;
  wire _021_;
  wire _022_;
  wire _023_;
  wire _024_;
  wire _025_;
  wire _026_;
  wire _027_;
  wire _028_;
  wire _029_;
  wire _030_;
  wire _031_;
  wire _032_;
  wire _033_;
  wire _034_;
  wire _035_;
  wire _036_;
  wire _037_;
  wire _038_;
  wire _039_;
  wire _040_;
  wire _041_;
  wire _042_;
  wire _043_;
  wire _044_;
  wire _045_;
  wire _046_;
  wire _047_;
  wire _048_;
  wire _049_;
  wire _050_;
  wire _051_;
  wire _052_;
  wire _053_;
  wire _054_;
  wire _055_;
  wire _056_;
  wire _057_;
  wire _058_;
  wire _059_;
  wire _060_;
  wire _061_;
  wire _062_;
  wire _063_;
  wire _064_;
  wire _065_;
  wire _066_;
  wire _067_;
  wire _068_;
  wire _069_;
  wire _070_;
  (* src = "ParaleloSerie_Est.v:19|<techmap.v>:142" *)
  wire [7:0] _071_;
  (* src = "ParaleloSerie_Est.v:19|<techmap.v>:145" *)
  wire [7:0] _072_;
  (* src = "ParaleloSerie_Est.v:19|<techmap.v>:145" *)
  wire [7:0] _073_;
  (* src = "<techmap.v>:260|<techmap.v>:203" *)
  wire [31:0] _074_;
  wire [31:0] _075_;
  (* src = "<techmap.v>:260|<techmap.v>:221" *)
  wire _076_;
  (* src = "ParaleloSerie_Est.v:4" *)
  input clk_8f;
  (* src = "ParaleloSerie_Est.v:5" *)
  input clk_f;
  (* src = "ParaleloSerie_Est.v:7" *)
  output [7:0] data2send_est;
  (* src = "ParaleloSerie_Est.v:2" *)
  input [7:0] data_inP;
  (* src = "ParaleloSerie_Est.v:8" *)
  output data_outS_est;
  (* src = "ParaleloSerie_Est.v:10" *)
  wire [2:0] out44_est;
  (* src = "ParaleloSerie_Est.v:10" *)
  wire [2:0] out44_estF;
  (* src = "ParaleloSerie_Est.v:3" *)
  input reset;
  (* src = "ParaleloSerie_Est.v:6" *)
  input valid_in;
  NOT _077_ (
    .A(_008_),
    .Y(_016_)
  );
  NOT _078_ (
    .A(_006_),
    .Y(_018_)
  );
  NOR _079_ (
    .A(_018_),
    .B(_016_),
    .Y(_019_)
  );
  NAND _080_ (
    .A(_019_),
    .B(_030_),
    .Y(_021_)
  );
  NOT _081_ (
    .A(_021_),
    .Y(_007_)
  );
  NAND _082_ (
    .A(_019_),
    .B(_002_),
    .Y(_023_)
  );
  NOT _083_ (
    .A(_023_),
    .Y(_009_)
  );
  NOT _084_ (
    .A(_040_),
    .Y(_024_)
  );
  NAND _085_ (
    .A(_019_),
    .B(_024_),
    .Y(_010_)
  );
  NAND _086_ (
    .A(_006_),
    .B(_008_),
    .Y(_026_)
  );
  NOR _087_ (
    .A(_026_),
    .B(_061_),
    .Y(_027_)
  );
  NOT _088_ (
    .A(_027_),
    .Y(_011_)
  );
  NOR _089_ (
    .A(_026_),
    .B(_070_),
    .Y(_028_)
  );
  NOT _090_ (
    .A(_028_),
    .Y(_012_)
  );
  NOR _091_ (
    .A(_026_),
    .B(_003_),
    .Y(_029_)
  );
  NOT _092_ (
    .A(_029_),
    .Y(_013_)
  );
  NOT _093_ (
    .A(_004_),
    .Y(_032_)
  );
  NOR _094_ (
    .A(_026_),
    .B(_032_),
    .Y(_014_)
  );
  NOT _095_ (
    .A(_005_),
    .Y(_034_)
  );
  NAND _096_ (
    .A(_019_),
    .B(_034_),
    .Y(_015_)
  );
  NOT _097_ (
    .A(_017_),
    .Y(_035_)
  );
  NOR _098_ (
    .A(_035_),
    .B(_018_),
    .Y(_037_)
  );
  NOT _099_ (
    .A(_022_),
    .Y(_038_)
  );
  NAND _100_ (
    .A(_027_),
    .B(_038_),
    .Y(_039_)
  );
  NOT _101_ (
    .A(_020_),
    .Y(_041_)
  );
  NOR _102_ (
    .A(_015_),
    .B(_038_),
    .Y(_042_)
  );
  NOR _103_ (
    .A(_042_),
    .B(_041_),
    .Y(_043_)
  );
  NAND _104_ (
    .A(_043_),
    .B(_039_),
    .Y(_044_)
  );
  NAND _105_ (
    .A(_038_),
    .B(_041_),
    .Y(_045_)
  );
  NOR _106_ (
    .A(_045_),
    .B(_023_),
    .Y(_046_)
  );
  NAND _107_ (
    .A(_022_),
    .B(_041_),
    .Y(_047_)
  );
  NOR _108_ (
    .A(_047_),
    .B(_029_),
    .Y(_048_)
  );
  NOR _109_ (
    .A(_048_),
    .B(_046_),
    .Y(_049_)
  );
  NAND _110_ (
    .A(_049_),
    .B(_044_),
    .Y(_050_)
  );
  NAND _111_ (
    .A(_050_),
    .B(_037_),
    .Y(_051_)
  );
  NAND _112_ (
    .A(_010_),
    .B(_038_),
    .Y(_052_)
  );
  NAND _113_ (
    .A(_014_),
    .B(_022_),
    .Y(_053_)
  );
  NAND _114_ (
    .A(_053_),
    .B(_052_),
    .Y(_054_)
  );
  NAND _115_ (
    .A(_054_),
    .B(_020_),
    .Y(_055_)
  );
  NOR _116_ (
    .A(_045_),
    .B(_021_),
    .Y(_056_)
  );
  NOR _117_ (
    .A(_047_),
    .B(_028_),
    .Y(_057_)
  );
  NOR _118_ (
    .A(_057_),
    .B(_056_),
    .Y(_058_)
  );
  NAND _119_ (
    .A(_058_),
    .B(_055_),
    .Y(_059_)
  );
  NOR _120_ (
    .A(_017_),
    .B(_018_),
    .Y(_060_)
  );
  NAND _121_ (
    .A(_060_),
    .B(_059_),
    .Y(_062_)
  );
  NAND _122_ (
    .A(_062_),
    .B(_051_),
    .Y(_025_)
  );
  NOT _123_ (
    .A(_037_),
    .Y(_031_)
  );
  NAND _124_ (
    .A(_020_),
    .B(_017_),
    .Y(_063_)
  );
  NOR _125_ (
    .A(_020_),
    .B(_017_),
    .Y(_064_)
  );
  NOR _126_ (
    .A(_064_),
    .B(_018_),
    .Y(_065_)
  );
  NAND _127_ (
    .A(_065_),
    .B(_063_),
    .Y(_033_)
  );
  NOT _128_ (
    .A(_065_),
    .Y(_066_)
  );
  NOR _129_ (
    .A(_066_),
    .B(_022_),
    .Y(_067_)
  );
  NOT _130_ (
    .A(_060_),
    .Y(_068_)
  );
  NOR _131_ (
    .A(_068_),
    .B(_047_),
    .Y(_069_)
  );
  NOR _132_ (
    .A(_069_),
    .B(_067_),
    .Y(_036_)
  );
  DFF _133_ (
    .C(clk_8f),
    .D(_000_[0]),
    .Q(out44_estF[0])
  );
  DFF _134_ (
    .C(clk_8f),
    .D(_000_[1]),
    .Q(out44_estF[1])
  );
  DFF _135_ (
    .C(clk_8f),
    .D(_000_[2]),
    .Q(out44_estF[2])
  );
  assign _002_ = data_inP[1];
  assign _008_ = valid_in;
  assign _040_ = data_inP[2];
  assign _061_ = data_inP[3];
  assign _070_ = data_inP[4];
  assign _003_ = data_inP[5];
  assign _004_ = data_inP[6];
  assign _005_ = data_inP[7];
  assign _006_ = reset;
  assign data2send_est[0] = _007_;
  assign data2send_est[1] = _009_;
  assign data2send_est[2] = _010_;
  assign data2send_est[3] = _011_;
  assign data2send_est[4] = _012_;
  assign data2send_est[5] = _013_;
  assign data2send_est[6] = _014_;
  assign data2send_est[7] = _015_;
  assign _017_ = out44_estF[0];
  assign _020_ = out44_estF[1];
  assign _022_ = out44_estF[2];
  assign data_outS_est = _025_;
  assign _030_ = data_inP[0];
  assign _000_[0] = _031_;
  assign _000_[1] = _033_;
  assign _000_[2] = _036_;
endmodule

ParaleloSerie/probador.v
module probador(
    output reg clk_8f,
    output reg valid_in,
    output reg [7:0]data_inP,
    output reg reset,
    input [7:0]data2send,
    input data_outS,
    output reg clk_f);


    initial begin
	$dumpfile("ParaleloSerie.vcd");
	$dumpvars;
    reset = 0;
    @(posedge clk_f)
    reset = 1;
    valid_in<=0;
    @(posedge clk_f)
    valid_in<=1;
    data_inP<='hAA;
    @(posedge clk_f)
    data_inP<='hBB;
    @(posedge clk_f)
    data_inP<='hAC;
    @(posedge clk_f)
    valid_in <=0;




    #100 $finish;
    end

    initial clk_f <= 0;
      always #8 clk_f<= ~clk_f;
    initial clk_8f <=1;
      always #1 clk_8f<= ~clk_8f;




endmodule

phy_tx/ParaleloSerie/ParaleloSerie.v
module ParaleloSerie (
  input [7:0] data_inP,
  input reset,
  input clk_8f,
  input clk_f,
  input valid_in,
  output reg  [7:0] data2send,
  output reg data_outS);

  reg [2:0] out44, out44F;
  reg [7:0] data2sendF;

  always @ (posedge clk_8f) begin
    out44F <= out44 -1;
    data2sendF <= data2send;
  end

  always @ ( * ) begin
    data_outS = data2send[out44F];
    out44 = out44F;
    if (reset == 1) begin
      if (valid_in == 1) begin
        data2send = data_inP;
      end else begin
        data2send = 'hBC;
      end
    end else begin
      out44 = 8;
      data_outS = 0;
      data2send = data2sendF;
    end
  end

endmodule // ParaleloSerie

ParaleloSerie/bancoprueba.v
`timescale 1ns/100ps
//`include "gen.v"
`include "probador.v"
`include "ParaleloSerie.v"
`include "ParaleloSerie_Est.v"
`include "cmos_cells.v"
//`include "Generador128f.v"
module bancoprueba;

    wire clk_f;
    wire clk_8f;
    wire valid_in;
    wire [7:0]data_inP;
    wire [7:0] data2send;
    wire  data_outS;
    wire [7:0] data2send_est;
    wire data_outS_est;
    wire reset;


ParaleloSerie ParaleloSerie (/*AUTOINST*/
			     // Outputs
			     .data2send		(data2send[7:0]),
			     .data_outS		(data_outS),
			     // Inputs
			     .data_inP		(data_inP[7:0]),
			     .reset		(reset),
			     .clk_8f		(clk_8f),
			     .clk_f		(clk_f),
			     .valid_in		(valid_in));
probador prob (/*AUTOINST*/
	       // Outputs
	       .clk_8f			(clk_8f),
	       .valid_in		(valid_in),
	       .data_inP		(data_inP[7:0]),
	       .reset			(reset),
	       .clk_f			(clk_f),
	       // Inputs
	       .data2send		(data2send[7:0]),
	       .data_outS		(data_outS));
ParaleloSerie_Est ParaleloSerie_Est_(/*AUTOINST*/
				     // Outputs
				     .data2send_est	(data2send_est[7:0]),
				     .data_outS_est	(data_outS_est),
				     // Inputs
				     .clk_8f		(clk_8f),
				     .clk_f		(clk_f),
				     .data_inP		(data_inP[7:0]),
				     .reset		(reset),
				     .valid_in		(valid_in));


endmodule

phy/phy_rx/cmos_cells.v
module BUF(A, Y);
input A;
output Y;
assign Y = A;
endmodule

module NOT(A, Y);
input A;
output Y;
assign  Y = ~A;
endmodule

module NAND(A, B, Y);
input A, B;
output Y;
assign Y = ~(A & B);
endmodule

module NOR(A, B, Y);
input A, B;
output Y;
assign Y = ~(A | B);
endmodule

module DFF(C, D, Q);
input C, D;
output reg Q;
always @(posedge C)
	Q <= D;
endmodule

module DFFSR(C, D, Q, S, R);
input C, D, S, R;
output reg Q;
always @(posedge C, posedge S, posedge R)
	if (S)
		Q <= 1'b1;
	else if (R)
		Q <= 1'b0;
	else
		Q <= D;
endmodule

phy_tx/ParaleloSerie/ParaleloSerie.vcd
$date
	Wed May 22 19:54:04 2019
$end
$version
	Icarus Verilog
$end
$timescale
	100ps
$end
$scope module BUF $end
$var wire 1 ! A $end
$var wire 1 " Y $end
$upscope $end
$scope module DFFSR $end
$var wire 1 # C $end
$var wire 1 $ D $end
$var wire 1 % R $end
$var wire 1 & S $end
$var reg 1 ' Q $end
$upscope $end
$scope module bancoprueba $end
$var wire 1 ( clk_8f $end
$var wire 1 ) clk_f $end
$var wire 8 * data2send [7:0] $end
$var wire 8 + data2send_est [7:0] $end
$var wire 8 , data_inP [7:0] $end
$var wire 1 - data_outS $end
$var wire 1 . data_outS_est $end
$var wire 1 / reset $end
$var wire 1 0 valid_in $end
$scope module ParaleloSerie $end
$var wire 1 ( clk_8f $end
$var wire 1 ) clk_f $end
$var wire 8 1 data_inP [7:0] $end
$var wire 1 / reset $end
$var wire 1 0 valid_in $end
$var reg 8 2 data2send [7:0] $end
$var reg 8 3 data2sendF [7:0] $end
$var reg 1 4 data_outS $end
$var reg 3 5 out44 [2:0] $end
$var reg 3 6 out44F [2:0] $end
$upscope $end
$scope module prob $end
$var wire 8 7 data2send [7:0] $end
$var wire 1 - data_outS $end
$var reg 1 8 clk_8f $end
$var reg 1 9 clk_f $end
$var reg 8 : data_inP [7:0] $end
$var reg 1 ; reset $end
$var reg 1 < valid_in $end
$upscope $end
$scope module ParaleloSerie_Est_ $end
$var wire 3 = _000_ [2:0] $end
$var wire 1 > _002_ $end
$var wire 1 ? _003_ $end
$var wire 1 @ _004_ $end
$var wire 1 A _005_ $end
$var wire 1 B _006_ $end
$var wire 1 C _007_ $end
$var wire 1 D _008_ $end
$var wire 1 E _009_ $end
$var wire 1 F _010_ $end
$var wire 1 G _011_ $end
$var wire 1 H _012_ $end
$var wire 1 I _013_ $end
$var wire 1 J _014_ $end
$var wire 1 K _015_ $end
$var wire 1 L _016_ $end
$var wire 1 M _017_ $end
$var wire 1 N _018_ $end
$var wire 1 O _019_ $end
$var wire 1 P _020_ $end
$var wire 1 Q _021_ $end
$var wire 1 R _022_ $end
$var wire 1 S _023_ $end
$var wire 1 T _024_ $end
$var wire 1 U _025_ $end
$var wire 1 V _026_ $end
$var wire 1 W _027_ $end
$var wire 1 X _028_ $end
$var wire 1 Y _029_ $end
$var wire 1 Z _030_ $end
$var wire 1 [ _031_ $end
$var wire 1 \ _032_ $end
$var wire 1 ] _033_ $end
$var wire 1 ^ _034_ $end
$var wire 1 _ _035_ $end
$var wire 1 ` _036_ $end
$var wire 1 a _037_ $end
$var wire 1 b _038_ $end
$var wire 1 c _039_ $end
$var wire 1 d _040_ $end
$var wire 1 e _041_ $end
$var wire 1 f _042_ $end
$var wire 1 g _043_ $end
$var wire 1 h _044_ $end
$var wire 1 i _045_ $end
$var wire 1 j _046_ $end
$var wire 1 k _047_ $end
$var wire 1 l _048_ $end
$var wire 1 m _049_ $end
$var wire 1 n _050_ $end
$var wire 1 o _051_ $end
$var wire 1 p _052_ $end
$var wire 1 q _053_ $end
$var wire 1 r _054_ $end
$var wire 1 s _055_ $end
$var wire 1 t _056_ $end
$var wire 1 u _057_ $end
$var wire 1 v _058_ $end
$var wire 1 w _059_ $end
$var wire 1 x _060_ $end
$var wire 1 y _061_ $end
$var wire 1 z _062_ $end
$var wire 1 { _063_ $end
$var wire 1 | _064_ $end
$var wire 1 } _065_ $end
$var wire 1 ~ _066_ $end
$var wire 1 !" _067_ $end
$var wire 1 "" _068_ $end
$var wire 1 #" _069_ $end
$var wire 1 $" _070_ $end
$var wire 1 ( clk_8f $end
$var wire 1 ) clk_f $end
$var wire 8 %" data2send_est [7:0] $end
$var wire 8 &" data_inP [7:0] $end
$var wire 1 . data_outS_est $end
$var wire 3 '" out44_estF [2:0] $end
$var wire 1 / reset $end
$var wire 1 0 valid_in $end
$scope module _077_ $end
$var wire 1 D A $end
$var wire 1 L Y $end
$upscope $end
$scope module _078_ $end
$var wire 1 B A $end
$var wire 1 N Y $end
$upscope $end
$scope module _079_ $end
$var wire 1 N A $end
$var wire 1 L B $end
$var wire 1 O Y $end
$upscope $end
$scope module _080_ $end
$var wire 1 O A $end
$var wire 1 Z B $end
$var wire 1 Q Y $end
$upscope $end
$scope module _081_ $end
$var wire 1 Q A $end
$var wire 1 C Y $end
$upscope $end
$scope module _082_ $end
$var wire 1 O A $end
$var wire 1 > B $end
$var wire 1 S Y $end
$upscope $end
$scope module _083_ $end
$var wire 1 S A $end
$var wire 1 E Y $end
$upscope $end
$scope module _084_ $end
$var wire 1 d A $end
$var wire 1 T Y $end
$upscope $end
$scope module _085_ $end
$var wire 1 O A $end
$var wire 1 T B $end
$var wire 1 F Y $end
$upscope $end
$scope module _086_ $end
$var wire 1 B A $end
$var wire 1 D B $end
$var wire 1 V Y $end
$upscope $end
$scope module _087_ $end
$var wire 1 V A $end
$var wire 1 y B $end
$var wire 1 W Y $end
$upscope $end
$scope module _088_ $end
$var wire 1 W A $end
$var wire 1 G Y $end
$upscope $end
$scope module _089_ $end
$var wire 1 V A $end
$var wire 1 $" B $end
$var wire 1 X Y $end
$upscope $end
$scope module _090_ $end
$var wire 1 X A $end
$var wire 1 H Y $end
$upscope $end
$scope module _091_ $end
$var wire 1 V A $end
$var wire 1 ? B $end
$var wire 1 Y Y $end
$upscope $end
$scope module _092_ $end
$var wire 1 Y A $end
$var wire 1 I Y $end
$upscope $end
$scope module _093_ $end
$var wire 1 @ A $end
$var wire 1 \ Y $end
$upscope $end
$scope module _094_ $end
$var wire 1 V A $end
$var wire 1 \ B $end
$var wire 1 J Y $end
$upscope $end
$scope module _095_ $end
$var wire 1 A A $end
$var wire 1 ^ Y $end
$upscope $end
$scope module _096_ $end
$var wire 1 O A $end
$var wire 1 ^ B $end
$var wire 1 K Y $end
$upscope $end
$scope module _097_ $end
$var wire 1 M A $end
$var wire 1 _ Y $end
$upscope $end
$scope module _098_ $end
$var wire 1 _ A $end
$var wire 1 N B $end
$var wire 1 a Y $end
$upscope $end
$scope module _099_ $end
$var wire 1 R A $end
$var wire 1 b Y $end
$upscope $end
$scope module _100_ $end
$var wire 1 W A $end
$var wire 1 b B $end
$var wire 1 c Y $end
$upscope $end
$scope module _101_ $end
$var wire 1 P A $end
$var wire 1 e Y $end
$upscope $end
$scope module _102_ $end
$var wire 1 K A $end
$var wire 1 b B $end
$var wire 1 f Y $end
$upscope $end
$scope module _103_ $end
$var wire 1 f A $end
$var wire 1 e B $end
$var wire 1 g Y $end
$upscope $end
$scope module _104_ $end
$var wire 1 g A $end
$var wire 1 c B $end
$var wire 1 h Y $end
$upscope $end
$scope module _105_ $end
$var wire 1 b A $end
$var wire 1 e B $end
$var wire 1 i Y $end
$upscope $end
$scope module _106_ $end
$var wire 1 i A $end
$var wire 1 S B $end
$var wire 1 j Y $end
$upscope $end
$scope module _107_ $end
$var wire 1 R A $end
$var wire 1 e B $end
$var wire 1 k Y $end
$upscope $end
$scope module _108_ $end
$var wire 1 k A $end
$var wire 1 Y B $end
$var wire 1 l Y $end
$upscope $end
$scope module _109_ $end
$var wire 1 l A $end
$var wire 1 j B $end
$var wire 1 m Y $end
$upscope $end
$scope module _110_ $end
$var wire 1 m A $end
$var wire 1 h B $end
$var wire 1 n Y $end
$upscope $end
$scope module _111_ $end
$var wire 1 n A $end
$var wire 1 a B $end
$var wire 1 o Y $end
$upscope $end
$scope module _112_ $end
$var wire 1 F A $end
$var wire 1 b B $end
$var wire 1 p Y $end
$upscope $end
$scope module _113_ $end
$var wire 1 J A $end
$var wire 1 R B $end
$var wire 1 q Y $end
$upscope $end
$scope module _114_ $end
$var wire 1 q A $end
$var wire 1 p B $end
$var wire 1 r Y $end
$upscope $end
$scope module _115_ $end
$var wire 1 r A $end
$var wire 1 P B $end
$var wire 1 s Y $end
$upscope $end
$scope module _116_ $end
$var wire 1 i A $end
$var wire 1 Q B $end
$var wire 1 t Y $end
$upscope $end
$scope module _117_ $end
$var wire 1 k A $end
$var wire 1 X B $end
$var wire 1 u Y $end
$upscope $end
$scope module _118_ $end
$var wire 1 u A $end
$var wire 1 t B $end
$var wire 1 v Y $end
$upscope $end
$scope module _119_ $end
$var wire 1 v A $end
$var wire 1 s B $end
$var wire 1 w Y $end
$upscope $end
$scope module _120_ $end
$var wire 1 M A $end
$var wire 1 N B $end
$var wire 1 x Y $end
$upscope $end
$scope module _121_ $end
$var wire 1 x A $end
$var wire 1 w B $end
$var wire 1 z Y $end
$upscope $end
$scope module _122_ $end
$var wire 1 z A $end
$var wire 1 o B $end
$var wire 1 U Y $end
$upscope $end
$scope module _123_ $end
$var wire 1 a A $end
$var wire 1 [ Y $end
$upscope $end
$scope module _124_ $end
$var wire 1 P A $end
$var wire 1 M B $end
$var wire 1 { Y $end
$upscope $end
$scope module _125_ $end
$var wire 1 P A $end
$var wire 1 M B $end
$var wire 1 | Y $end
$upscope $end
$scope module _126_ $end
$var wire 1 | A $end
$var wire 1 N B $end
$var wire 1 } Y $end
$upscope $end
$scope module _127_ $end
$var wire 1 } A $end
$var wire 1 { B $end
$var wire 1 ] Y $end
$upscope $end
$scope module _128_ $end
$var wire 1 } A $end
$var wire 1 ~ Y $end
$upscope $end
$scope module _129_ $end
$var wire 1 ~ A $end
$var wire 1 R B $end
$var wire 1 !" Y $end
$upscope $end
$scope module _130_ $end
$var wire 1 x A $end
$var wire 1 "" Y $end
$upscope $end
$scope module _131_ $end
$var wire 1 "" A $end
$var wire 1 k B $end
$var wire 1 #" Y $end
$upscope $end
$scope module _132_ $end
$var wire 1 #" A $end
$var wire 1 !" B $end
$var wire 1 ` Y $end
$upscope $end
$scope module _133_ $end
$var wire 1 ( C $end
$var wire 1 (" D $end
$var reg 1 )" Q $end
$upscope $end
$scope module _134_ $end
$var wire 1 ( C $end
$var wire 1 *" D $end
$var reg 1 +" Q $end
$upscope $end
$scope module _135_ $end
$var wire 1 ( C $end
$var wire 1 ," D $end
$var reg 1 -" Q $end
$upscope $end
$upscope $end
$upscope $end
$enddefinitions $end
#0
$dumpvars
1-"
1,"
1+"
1*"
1)"
1("
b111 '"
bx &"
b10111100 %"
x$"
0#"
1""
0!"
1~
0}
0|
0{
1z
xy
0x
0w
1v
0u
0t
1s
0r
1q
1p
1o
1n
1m
0l
1k
0j
1i
0h
1g
0f
0e
xd
1c
0b
0a
1`
0_
x^
1]
x\
1[
xZ
0Y
0X
0W
1V
0U
xT
1S
1R
1Q
1P
0O
1N
1M
xL
1K
0J
1I
1H
1G
1F
0E
xD
0C
0B
xA
x@
x?
x>
b111 =
x<
0;
bx :
09
18
b10111100 7
b111 6
b0 5
04
b10111100 3
b10111100 2
bx 1
x0
0/
0.
0-
bx ,
b10111100 +
b10111100 *
0)
1(
x'
z&
z%
z$
z#
z"
z!
$end
#10
08
0(
#20
18
1(
#30
08
0(
#40
18
1(
#50
08
0(
#60
18
1(
#70
08
0(
#80
1L
0<
0D
00
1n
0w
0h
1s
1g
0r
0f
1U
1.
0C
0E
1q
1Q
1S
1F
1K
0o
0("
1G
1H
1I
0[
b110 =
0~
0W
0X
0Y
0J
b10111100 +
b10111100 %"
0O
1a
1}
1V
0N
b111 5
14
1-
1;
1B
1/
18
1(
19
1)
#90
08
0(
#100
0U
0.
1o
1("
0*"
1[
0]
b101 =
0a
0""
1x
1{
1_
0M
b110 5
04
0-
0)"
b110 '"
b110 6
18
1(
#110
08
0(
#120
1w
1U
1.
1n
0m
0v
0o
0("
1h
1l
1u
0[
b100 =
1a
1""
0g
0k
0x
0_
1e
b101 5
14
1-
1M
0P
b101 6
1)"
0+"
b101 '"
18
1(
#130
08
0(
#140
0,"
0`
1*"
1]
1o
1("
1#"
1~
1[
b11 =
0z
0}
0a
0""
1x
1|
1_
0M
b100 5
0)"
b100 '"
b100 6
18
1(
#150
08
0(
#160
1w
1!"
0s
0,"
1U
1.
1m
1v
0`
0o
0("
0h
0~
1r
0[
b10 =
1z
1}
0l
0u
0#"
1a
1""
1g
0p
0x
0{
0|
1k
0_
0e
1b
b11 5
1M
1P
0R
b11 6
1)"
1+"
0-"
b11 '"
18
1(
09
0)
#170
08
0(
#180
1o
1("
0*"
1[
0z
0]
b1 =
0a
0""
1x
1{
1_
0M
b10 5
0)"
b10 '"
b10 6
18
1(
#190
08
0(
#200
0n
0U
0.
1o
0("
1h
0[
b0 =
1z
0w
1a
1""
0g
0i
0x
1s
0_
1e
b1 5
04
0-
1M
0P
b1 6
1)"
0+"
b1 '"
18
1(
#210
08
0(
#220
1,"
1`
1*"
0!"
1]
1("
1~
1[
b111 =
0}
0a
0""
1x
1|
1_
0M
b0 5
0)"
b0 '"
b0 6
18
1(
#230
08
0(
#240
1U
1.
0o
1n
1,"
1m
1`
0("
0h
0~
0r
1E
0[
b110 =
0w
1}
0l
0#"
0S
1a
1""
1g
1i
1p
0F
0H
b10101010 +
b10101010 %"
0x
1s
0{
0|
1k
1X
1O
0_
0e
0b
1T
1\
0^
0V
1M
1P
1R
1>
0d
1y
0$"
1?
0@
1A
0Z
0L
b10101010 2
b10101010 *
b10101010 7
b111 5
14
1-
b111 6
1)"
1+"
1-"
b111 '"
b10101010 :
b10101010 ,
b10101010 1
b10101010 &"
1<
1D
10
18
1(
19
1)
#250
08
0(
#260
0U
0.
1o
1("
0*"
1[
0]
b101 =
0a
0""
1x
1{
1_
0M
b110 5
04
0-
0)"
b110 '"
b10101010 3
b110 6
18
1(
#270
08
0(
#280
1U
1.
1n
0m
0o
0("
1h
1l
0[
b100 =
1a
1""
0g
0k
0x
0_
1e
b101 5
14
1-
1M
0P
b101 6
1)"
0+"
b101 '"
18
1(
#290
08
0(
#300
0,"
0U
0.
0`
1*"
1]
1o
1("
1#"
1~
1[
b11 =
0}
0a
0""
1x
1|
1_
0M
b100 5
04
0-
0)"
b100 '"
b100 6
18
1(
#310
08
0(
#320
1U
1.
1!"
0,"
1m
0`
0o
0("
0h
0~
0[
b10 =
1}
0l
0#"
1a
1""
1g
0x
0{
0|
1k
0_
0e
1b
b11 5
14
1-
1M
1P
0R
b11 6
1)"
1+"
0-"
b11 '"
18
1(
09
0)
#330
08
0(
#340
0U
0.
1o
1("
0*"
1[
0]
b1 =
0a
0""
1x
1{
1_
0M
b10 5
04
0-
0)"
b10 '"
b10 6
18
1(
#350
08
0(
#360
1U
1.
1n
0m
0o
0("
1h
1j
0[
b0 =
1a
1""
0g
0i
0x
0_
1e
b1 5
14
1-
1M
0P
b1 6
1)"
0+"
b1 '"
18
1(
#370
08
0(
#380
1,"
1`
0U
0.
1*"
0!"
1]
1o
1("
1~
1[
b111 =
0}
0a
0""
1x
1|
1_
0M
b0 5
04
0-
0)"
b0 '"
b0 6
18
1(
#390
08
0(
#400
0w
1U
1.
1m
1,"
1`
1v
0o
0("
0h
0~
0j
0[
b110 =
1}
0l
0#"
0u
0t
1a
1""
1g
1i
1H
1C
b10111011 +
b10111011 %"
0x
0{
0|
1k
0X
0Q
0_
0e
0b
1M
1P
1R
1$"
1Z
b10111011 2
b10111011 *
b10111011 7
b111 5
14
1-
b111 6
1)"
1+"
1-"
b111 '"
b10111011 :
b10111011 ,
b10111011 1
b10111011 &"
18
1(
19
1)
#410
08
0(
#420
0U
0.
1o
1("
0*"
1[
0]
b101 =
0a
0""
1x
1{
1_
0M
b110 5
04
0-
0)"
b110 '"
b10111011 3
b110 6
18
1(
#430
08
0(
#440
1w
1U
1.
1n
0m
0v
0o
0("
1h
1l
1u
0[
b100 =
1a
1""
0g
0k
0x
0_
1e
b101 5
14
1-
1M
0P
b101 6
1)"
0+"
b101 '"
18
1(
#450
08
0(
#460
0,"
0`
1*"
1]
1o
1("
1#"
1~
1[
b11 =
0z
0}
0a
0""
1x
1|
1_
0M
b100 5
0)"
b100 '"
b100 6
18
1(
#470
08
0(
#480
0w
1!"
0,"
1U
1.
1m
1v
0`
0o
0("
0h
0~
0[
b10 =
1z
1}
0l
0u
0#"
1a
1""
1g
0x
0{
0|
1k
0_
0e
1b
b11 5
1M
1P
0R
b11 6
1)"
1+"
0-"
b11 '"
18
1(
09
0)
#490
08
0(
#500
0U
0.
1o
1("
0*"
1[
0]
b1 =
0a
0""
1x
1{
1_
0M
b10 5
04
0-
0)"
b10 '"
b10 6
18
1(
#510
08
0(
#520
1w
1U
1.
1n
0m
0v
0o
0("
1h
1j
1t
0[
b0 =
1a
1""
0g
0i
0x
0_
1e
b1 5
14
1-
1M
0P
b1 6
1)"
0+"
b1 '"
18
1(
#530
08
0(
#540
1,"
1`
1*"
0!"
1]
1o
1("
1~
1[
b111 =
0z
0}
0a
0""
1x
1|
1_
0M
b0 5
0)"
b0 '"
b0 6
18
1(
#550
08
0(
#560
0w
1m
1,"
1U
1.
1`
1v
0o
0("
0h
0~
0[
b110 =
1z
1}
0l
0#"
0j
0t
1a
1""
1g
1i
0E
1F
0H
0C
b10101100 +
b10101100 %"
0x
0{
0|
1k
1S
1X
1Q
0_
0e
0b
0T
1M
1P
1R
0>
1d
0$"
0Z
b10101100 2
b10101100 *
b10101100 7
b111 5
b111 6
1)"
1+"
1-"
b111 '"
b10101100 :
b10101100 ,
b10101100 1
b10101100 &"
18
1(
19
1)
#570
08
0(
#580
0U
0.
1o
1("
0*"
1[
0]
b101 =
0a
0""
1x
1{
1_
0M
b110 5
04
0-
0)"
b110 '"
b10101100 3
b110 6
18
1(
#590
08
0(
