GeneradorSenales/Generador128f_Est.v
/* Generated by Yosys 0.8+463 (git sha1 5772732a, clang 6.0.0-1ubuntu2 -fPIC -Os) */

(* top =  1  *)
(* src = " Generador128f_Est.v:1" *)
module  Generador128f_Est(clk_8f, reset, clk_f_Est, clk_2f_Est);
  (* src = " Generador128f_Est.v:9" *)
  wire _00_;
  (* src = " Generador128f_Est.v:9" *)
  wire _01_;
  (* src = " Generador128f_Est.v:9" *)
  wire [1:0] _02_;
  (* src = " Generador128f_Est.v:15" *)
  (* unused_bits = "2" *)
  wire [31:0] _03_;
  wire _04_;
  wire [1:0] _05_;
  wire _06_;
  (* src = " Generador128f_Est.v:16" *)
  wire _07_;
  (* src = " Generador128f_Est.v:16" *)
  wire _08_;
  (* src = " Generador128f_Est.v:16" *)
  wire _09_;
  (* src = " Generador128f_Est.v:17" *)
  wire _10_;
  (* src = " Generador128f_Est.v:22" *)
  wire _11_;
  wire _12_;
  wire _13_;
  (* src = " Generador128f_Est.v:5" *)
  output clk_2f_Est;
  reg clk_2f_Est;
  (* src = " Generador128f_Est.v:2" *)
  input clk_8f;
  (* src = " Generador128f_Est.v:4" *)
  output clk_f_Est;
  reg clk_f_Est;
  (* src = " Generador128f_Est.v:7" *)
  reg [1:0] contador;
  (* src = " Generador128f_Est.v:3" *)
  input reset;
  assign _06_ = contador[0] |(* src = " Generador128f_Est.v:21" *)  _05_[1];
  assign _04_ = contador[0] |(* src = " Generador128f_Est.v:16" *)  contador[1];
  assign _07_ = ~(* src = " Generador128f_Est.v:16" *) _04_;
  assign _08_ = ~(* src = " Generador128f_Est.v:21" *) _06_;
  assign _09_ = _07_ |(* src = " Generador128f_Est.v:16" *)  _08_;
  assign _12_ = _09_ ? (* src = " Generador128f_Est.v:16" *) _10_ : clk_2f_Est;
  assign _00_ = reset ? (* src = " Generador128f_Est.v:10" *) _12_ : 1'h0;
  assign _13_ = _06_ ? (* src = " Generador128f_Est.v:21" *) clk_f_Est : _11_;
  assign _01_ = reset ? (* src = " Generador128f_Est.v:10" *) _13_ : 1'h0;
  assign _02_[0] = reset ? (* src = " Generador128f_Est.v:10" *) _03_[0] : 1'h0;
  assign _02_[1] = reset ? (* src = " Generador128f_Est.v:10" *) _03_[1] : 1'h0;
  assign _10_ = ~(* src = " Generador128f_Est.v:17" *) clk_2f_Est;
  assign _11_ = ~(* src = " Generador128f_Est.v:22" *) clk_f_Est;
  (* src = " Generador128f_Est.v:9" *)
  always @(posedge clk_8f)
      clk_2f_Est <= _00_;
  (* src = " Generador128f_Est.v:9" *)
  always @(posedge clk_8f)
      contador[0] <= _02_[0];
  (* src = " Generador128f_Est.v:9" *)
  always @(posedge clk_8f)
      contador[1] <= _02_[1];
  (* src = " Generador128f_Est.v:9" *)
  always @(posedge clk_8f)
      clk_f_Est <= _01_;
  assign _03_[1] = contador[1] ^(* src = " Generador128f_Est.v:15|<techmap.v>:263" *)  contador[0];
  assign _03_[0] = contador[0] ^(* src = " Generador128f_Est.v:15|<techmap.v>:262" *)  1'h1;
  assign _05_[1] = contador[1] ^(* src = " Generador128f_Est.v:21" *)  1'h1;
  assign _03_[31:3] = 29'h00000000;
  assign _05_[0] = contador[0];
endmodule

Documents/digitales_2/proyecto/GeneradorSenales/Generador128f.v
module Generador128f (
  input clk_8f,
  input reset,
  output reg clk_f,
  output reg clk_2f);

  reg [1:0] contador;

  always @ (posedge clk_8f) begin
    if (reset == 0) begin
      contador <= 0;
      clk_2f <= 0;
      clk_f <= 0;
    end else begin
      contador <= contador + 1;
      if (contador == 0 || contador == 2) begin
        clk_2f <= ~clk_2f;
      end else begin
        clk_2f <= clk_2f;
      end
      if (contador == 2) begin
        clk_f <= ~clk_f;
      end else begin
        clk_f <= clk_f;
      end
    end
  end
endmodule //Generador12clk_8f

Documents/digitales_2/proyecto/GeneradorSenales/ProbadorGenerador.v
module ProbadorGenerador (
  input clk_f,
  input clk_2f,
  input clk_f_Est,
  input clk_2f_Est,
  output reg clk_8f,
  output reg reset);

  reg contar;
  initial begin
		$dumpfile("Generador128f.vcd");	// Nombre de archivo del "dump"
		$dumpvars;
    reset = 0;
    contar = 0;
    @(posedge clk_8f);
    reset <= 1;
    repeat(16)
      @(posedge clk_8f);
      contar = contar+1;
		$finish;
	end
  initial	clk_8f <= 0;
	always	#1 clk_8f <= ~clk_8f;

endmodule //ProbadorGenerador

Documents/digitales_2/proyecto/GeneradorSenales/BancoGenerador.v
`timescale 1ns/100ps
`include "ProbadorGenerador.v"
`include "Generador128f.v"
`include "Generador128f_Est.v"

module BancoGenerador;
  wire clk_f;
  wire clk_2f;
  wire clk_8f;
  wire clk_f_Est;
  wire clk_2f_Est;
  wire reset;

  ProbadorGenerador ProbadorGenerador_(/*autoinst*/
				       // Outputs
				       .clk_8f		(clk_8f),
				       .reset		(reset),
				       // Inputs
				       .clk_f		(clk_f),
				       .clk_2f		(clk_2f),
				       .clk_f_Est	(clk_f_Est),
				       .clk_2f_Est	(clk_2f_Est));
  Generador128f Generador128f_(/*autoinst*/
			       // Outputs
			       .clk_f		(clk_f),
			       .clk_2f		(clk_2f),
			       // Inputs
			       .clk_8f		(clk_8f),
			       .reset		(reset));
  Generador128f_Est Generador128f_Est_(/*autoinst*/
				       // Outputs
				       .clk_2f_Est	(clk_2f_Est),
				       .clk_f_Est	(clk_f_Est),
				       // Inputs
				       .clk_8f		(clk_8f),
				       .reset		(reset));

endmodule // BancoGenerador

GeneradorSenales/Generador128f.vcd
$date
	Wed May 15 14:50:08 2019
$end
$version
	Icarus Verilog
$end
$timescale
	100ps
$end
$scope module BancoGenerador $end
$var wire 1 ! reset $end
$var wire 1 " clk_f_Est $end
$var wire 1 # clk_f $end
$var wire 1 $ clk_8f $end
$var wire 1 % clk_2f_Est $end
$var wire 1 & clk_2f $end
$scope module Generador128f_ $end
$var wire 1 ! reset $end
$var wire 1 $ clk_8f $end
$var reg 1 & clk_2f $end
$var reg 1 # clk_f $end
$var reg 2 ' contador [1:0] $end
$upscope $end
$scope module Generador128f_Est_ $end
$var wire 1 ( _04_ $end
$var wire 1 ) _06_ $end
$var wire 1 * _07_ $end
$var wire 1 + _08_ $end
$var wire 1 , _09_ $end
$var wire 1 - _10_ $end
$var wire 1 . _11_ $end
$var wire 1 ! reset $end
$var wire 1 $ clk_8f $end
$var wire 1 / _13_ $end
$var wire 1 0 _12_ $end
$var wire 2 1 _05_ [1:0] $end
$var wire 32 2 _03_ [31:0] $end
$var wire 2 3 _02_ [1:0] $end
$var wire 1 4 _01_ $end
$var wire 1 5 _00_ $end
$var reg 1 % clk_2f_Est $end
$var reg 1 " clk_f_Est $end
$var reg 2 6 contador [1:0] $end
$upscope $end
$scope module ProbadorGenerador_ $end
$var wire 1 & clk_2f $end
$var wire 1 % clk_2f_Est $end
$var wire 1 # clk_f $end
$var wire 1 " clk_f_Est $end
$var reg 1 $ clk_8f $end
$var reg 1 7 contar $end
$var reg 1 ! reset $end
$upscope $end
$upscope $end
$enddefinitions $end
#0
$dumpvars
07
bx 6
05
04
b0 3
bzxx 2
bxz 1
x0
x/
x.
x-
x,
x+
x*
x)
x(
bx '
x&
x%
0$
x#
x"
0!
$end
#10
0+
0/
10
1)
1,
1*
b1z 1
0(
bz01 2
04
15
b1 3
1.
1-
1!
0#
0&
b0 '
0"
0%
b0 6
1$
#20
0$
#30
0,
b10 3
0*
15
1(
bz10 2
10
0-
b1 6
1%
1&
b1 '
1$
#40
0$
#50
05
00
1,
14
1+
1/
0)
b11 3
b0z 1
bz11 2
b10 '
b10 6
1$
#60
0$
#70
0,
b0 3
0+
05
14
1)
bz00 2
00
1/
1-
0.
b11 6
0%
1"
1#
0&
b11 '
1$
#80
0$
#90
15
10
14
1,
b1 3
0+
1/
1*
b1z 1
1)
0(
bz01 2
b0 '
b0 6
1$
#100
0$
#110
0,
b10 3
0*
15
1(
bz10 2
10
0-
b1 6
1%
1&
b1 '
1$
#120
0$
#130
05
00
1,
04
1+
0/
0)
b11 3
b0z 1
bz11 2
b10 '
b10 6
1$
#140
0$
#150
0,
b0 3
0+
05
04
1)
bz00 2
00
0/
1-
1.
b11 6
0%
0"
0#
0&
b11 '
1$
#160
0$
#170
15
10
04
1,
b1 3
0+
0/
1*
b1z 1
1)
0(
bz01 2
b0 '
b0 6
1$
#180
0$
#190
0,
b10 3
0*
15
1(
bz10 2
10
0-
b1 6
1%
1&
b1 '
1$
#200
0$
#210
05
00
1,
14
1+
1/
0)
b11 3
b0z 1
bz11 2
b10 '
b10 6
1$
#220
0$
#230
0,
b0 3
0+
05
14
1)
bz00 2
00
1/
1-
0.
b11 6
0%
1"
1#
0&
b11 '
1$
#240
0$
#250
15
10
14
1,
b1 3
0+
1/
1*
b1z 1
1)
0(
bz01 2
b0 '
b0 6
1$
#260
0$
#270
0,
b10 3
0*
15
1(
bz10 2
10
0-
b1 6
1%
1&
b1 '
1$
#280
0$
#290
05
00
1,
04
1+
0/
0)
b11 3
b0z 1
bz11 2
b10 '
b10 6
1$
#300
0$
#310
0,
b0 3
0+
05
04
1)
bz00 2
00
0/
1-
1.
b11 6
0%
0"
0#
0&
b11 '
1$
#320
0$
#330
15
10
04
1,
b1 3
0+
0/
1*
b1z 1
1)
0(
bz01 2
b0 '
b0 6
17
1$
