phy/Generador128f.v
module Generador128f (
  input clk_8f,
  input reset,
  output reg clk_f,
  output reg clk_2f);

  reg [1:0] contador;
  reg [3:0] contador2;

  always @ (posedge clk_8f) begin
    if (reset == 0) begin
      contador <= 0;
      contador2 <= 0;
      clk_2f <= 0;
      clk_f <= 0;
    end else begin
      contador <= contador + 1;
      contador2 <= contador2 + 1;
      if (contador == 0 || contador == 2) begin
        clk_2f <= ~clk_2f;
      end else begin
        clk_2f <= clk_2f;
      end
      if (contador2 == 0 || contador2 == 4) begin
        clk_f <= ~clk_f;
        if (contador2 == 4) begin
          contador2 <= 1;
        end
      end else begin
        clk_f <= clk_f;
      end
    end
  end
endmodule //Generador12clk_8f

phy/phy_rx/cmos_cells.v
module BUF(A, Y);
input A;
output Y;
assign Y = A;
endmodule

module NOT(A, Y);
input A;
output Y;
assign  Y = ~A;
endmodule

module NAND(A, B, Y);
input A, B;
output Y;
assign Y = ~(A & B);
endmodule

module NOR(A, B, Y);
input A, B;
output Y;
assign Y = ~(A | B);
endmodule

module DFF(C, D, Q);
input C, D;
output reg Q;
always @(posedge C)
	Q <= D;
endmodule

module DFFSR(C, D, Q, S, R);
input C, D, S, R;
output reg Q;
always @(posedge C, posedge S, posedge R)
	if (S)
		Q <= 1'b1;
	else if (R)
		Q <= 1'b0;
	else
		Q <= D;
endmodule

Documents/digitales_2/proyecto/ParaleloSerie/ParaleloSerie_Est.v
/* Generated by Yosys 0.8+285 (git sha1 a7ac8393, clang 6.0.0-1ubuntu2 -fPIC -Os) */

(* top =  1  *)
(* src = "ParaleloSerie_Est.v:1" *)
module ParaleloSerie_Est(data_inP, reset, clk_8f, clk_f, valid_in, data2send_est, data_outS_est);
  (* src = "ParaleloSerie_Est.v:13" *)
  wire [2:0] _00_;
  (* src = "ParaleloSerie_Est.v:18" *)
  wire [7:0] _01_;
  (* src = "ParaleloSerie_Est.v:19|<techmap.v>:142" *)
  wire [7:0] _02_;
  (* src = "ParaleloSerie_Est.v:19|<techmap.v>:145" *)
  wire [7:0] _03_;
  (* src = "ParaleloSerie_Est.v:19|<techmap.v>:145" *)
  wire [7:0] _04_;
  (* src = "ParaleloSerie_Est.v:14|<techmap.v>:260|<techmap.v>:203" *)
  wire [31:0] _05_;
  wire [31:0] _06_;
  (* src = "ParaleloSerie_Est.v:14|<techmap.v>:260|<techmap.v>:221" *)
  wire _07_;
  (* src = "ParaleloSerie_Est.v:4" *)
  input clk_8f;
  (* src = "ParaleloSerie_Est.v:5" *)
  input clk_f;
  (* src = "ParaleloSerie_Est.v:7" *)
  output [7:0] data2send_est;
  (* src = "ParaleloSerie_Est.v:11" *)
  reg [7:0] data2send_estF;
  (* src = "ParaleloSerie_Est.v:2" *)
  input [7:0] data_inP;
  (* src = "ParaleloSerie_Est.v:8" *)
  output data_outS_est;
  (* src = "ParaleloSerie_Est.v:10" *)
  wire [2:0] out44_est;
  (* src = "ParaleloSerie_Est.v:10" *)
  reg [2:0] out44_estF;
  (* src = "ParaleloSerie_Est.v:3" *)
  input reset;
  (* src = "ParaleloSerie_Est.v:6" *)
  input valid_in;
  assign _01_[0] = valid_in ? (* src = "ParaleloSerie_Est.v:22" *) data_inP[0] : 1'h0;
  assign _01_[1] = valid_in ? (* src = "ParaleloSerie_Est.v:22" *) data_inP[1] : 1'h0;
  assign _01_[2] = valid_in ? (* src = "ParaleloSerie_Est.v:22" *) data_inP[2] : 1'h1;
  assign _01_[3] = valid_in ? (* src = "ParaleloSerie_Est.v:22" *) data_inP[3] : 1'h1;
  assign _01_[4] = valid_in ? (* src = "ParaleloSerie_Est.v:22" *) data_inP[4] : 1'h1;
  assign _01_[5] = valid_in ? (* src = "ParaleloSerie_Est.v:22" *) data_inP[5] : 1'h1;
  assign _01_[6] = valid_in ? (* src = "ParaleloSerie_Est.v:22" *) data_inP[6] : 1'h0;
  assign _01_[7] = valid_in ? (* src = "ParaleloSerie_Est.v:22" *) data_inP[7] : 1'h1;
  assign data2send_est[0] = reset ? (* src = "ParaleloSerie_Est.v:21" *) _01_[0] : data2send_estF[0];
  assign data2send_est[1] = reset ? (* src = "ParaleloSerie_Est.v:21" *) _01_[1] : data2send_estF[1];
  assign data2send_est[2] = reset ? (* src = "ParaleloSerie_Est.v:21" *) _01_[2] : data2send_estF[2];
  assign data2send_est[3] = reset ? (* src = "ParaleloSerie_Est.v:21" *) _01_[3] : data2send_estF[3];
  assign data2send_est[4] = reset ? (* src = "ParaleloSerie_Est.v:21" *) _01_[4] : data2send_estF[4];
  assign data2send_est[5] = reset ? (* src = "ParaleloSerie_Est.v:21" *) _01_[5] : data2send_estF[5];
  assign data2send_est[6] = reset ? (* src = "ParaleloSerie_Est.v:21" *) _01_[6] : data2send_estF[6];
  assign data2send_est[7] = reset ? (* src = "ParaleloSerie_Est.v:21" *) _01_[7] : data2send_estF[7];
  assign data_outS_est = reset ? (* src = "ParaleloSerie_Est.v:21" *) _02_[0] : 1'h0;
  assign out44_est[0] = reset ? (* src = "ParaleloSerie_Est.v:21" *) out44_estF[0] : 1'h0;
  assign out44_est[1] = reset ? (* src = "ParaleloSerie_Est.v:21" *) out44_estF[1] : 1'h0;
  assign out44_est[2] = reset ? (* src = "ParaleloSerie_Est.v:21" *) out44_estF[2] : 1'h0;
  assign _04_[0] = out44_estF[1] ? (* src = "ParaleloSerie_Est.v:19|<techmap.v>:162" *) _03_[2] : _03_[0];
  assign _04_[1] = out44_estF[1] ? (* src = "ParaleloSerie_Est.v:19|<techmap.v>:162" *) _03_[3] : _03_[1];
  assign _02_[0] = out44_estF[0] ? (* src = "ParaleloSerie_Est.v:19|<techmap.v>:162" *) _04_[1] : _04_[0];
  assign _03_[0] = out44_estF[2] ? (* src = "ParaleloSerie_Est.v:19|<techmap.v>:162" *) data2send_est[4] : data2send_est[0];
  assign _03_[1] = out44_estF[2] ? (* src = "ParaleloSerie_Est.v:19|<techmap.v>:162" *) data2send_est[5] : data2send_est[1];
  assign _03_[2] = out44_estF[2] ? (* src = "ParaleloSerie_Est.v:19|<techmap.v>:162" *) data2send_est[6] : data2send_est[2];
  assign _03_[3] = out44_estF[2] ? (* src = "ParaleloSerie_Est.v:19|<techmap.v>:162" *) data2send_est[7] : data2send_est[3];
  (* src = "ParaleloSerie_Est.v:13" *)
  always @(posedge clk_8f)
      out44_estF[0] <= _00_[0];
  (* src = "ParaleloSerie_Est.v:13" *)
  always @(posedge clk_8f)
      out44_estF[1] <= _00_[1];
  (* src = "ParaleloSerie_Est.v:13" *)
  always @(posedge clk_8f)
      out44_estF[2] <= _00_[2];
  (* src = "ParaleloSerie_Est.v:13" *)
  always @(posedge clk_8f)
      data2send_estF[0] <= data2send_est[0];
  (* src = "ParaleloSerie_Est.v:13" *)
  always @(posedge clk_8f)
      data2send_estF[1] <= data2send_est[1];
  (* src = "ParaleloSerie_Est.v:13" *)
  always @(posedge clk_8f)
      data2send_estF[2] <= data2send_est[2];
  (* src = "ParaleloSerie_Est.v:13" *)
  always @(posedge clk_8f)
      data2send_estF[3] <= data2send_est[3];
  (* src = "ParaleloSerie_Est.v:13" *)
  always @(posedge clk_8f)
      data2send_estF[4] <= data2send_est[4];
  (* src = "ParaleloSerie_Est.v:13" *)
  always @(posedge clk_8f)
      data2send_estF[5] <= data2send_est[5];
  (* src = "ParaleloSerie_Est.v:13" *)
  always @(posedge clk_8f)
      data2send_estF[6] <= data2send_est[6];
  (* src = "ParaleloSerie_Est.v:13" *)
  always @(posedge clk_8f)
      data2send_estF[7] <= data2send_est[7];
  assign _00_[0] = out44_est[0] ^(* src = "ParaleloSerie_Est.v:14|<techmap.v>:263" *)  1'h1;
  assign _00_[1] = _06_[1] ^(* src = "ParaleloSerie_Est.v:14|<techmap.v>:263" *)  out44_est[0];
  assign _00_[2] = _06_[2] ^(* src = "ParaleloSerie_Est.v:14|<techmap.v>:263" *)  _05_[1];
  assign _06_[1] = out44_est[1] ^(* src = "ParaleloSerie_Est.v:14|<techmap.v>:262" *)  1'h1;
  assign _06_[2] = out44_est[2] ^(* src = "ParaleloSerie_Est.v:14|<techmap.v>:262" *)  1'h1;
  assign _07_ = _06_[1] &(* src = "ParaleloSerie_Est.v:14|<techmap.v>:260|<techmap.v>:221" *)  out44_est[0];
  assign _05_[1] = out44_est[1] |(* src = "ParaleloSerie_Est.v:14|<techmap.v>:260|<techmap.v>:221" *)  _07_;
endmodule

ParaleloSerie/probador.v
module probador(
    output reg clk_8f,
    output reg valid_in,
    output reg [7:0]data_inP,
    output reg reset,
    input [7:0]data2send,
    input data_outS,
    output reg clk_f);


    initial begin
	$dumpfile("ParaleloSerie.vcd");
	$dumpvars;
    reset = 0;
    @(posedge clk_f)
    reset = 1;
    valid_in<=0;
    @(posedge clk_f)
    valid_in<=1;
    data_inP<='hAA;
    @(posedge clk_f)
    data_inP<='hBB;
    @(posedge clk_f)
    data_inP<='hAC;
    @(posedge clk_f)
    valid_in <=0;




    #100 $finish;
    end

    initial clk_f <= 0;
      always #8 clk_f<= ~clk_f;
    initial clk_8f <=1;
      always #1 clk_8f<= ~clk_8f;




endmodule

phy_tx/ParaleloSerie.v
module ParaleloSerie (
  input [7:0] data_inP,
  input reset,
  input clk_8f,
  input clk_f,
  input valid_in,
  output reg  [7:0] data2send,
  output reg data_outS);

  reg [2:0] out44, out44F;
  reg [7:0] data2sendF, datainF;
	
/*  always @ (posedge clk_f) begin
	if (!reset) begin
		datainF <= 0;
	end
	else begin
		datainF <= data_inP;
	end
  end*/

  always @ (posedge clk_8f) begin
    out44F <= out44 -1;
    data2sendF <= data2send;
  end
  always @ (posedge clk_8f) begin
	if (!reset) begin
		
	end
	else begin

	end
  end

  always @ ( * ) begin
    data_outS = data2send[out44F];
    out44 = out44F;
    if (reset == 1) begin
      if (valid_in == 1) begin
        data2send = data_inP;
      end else begin
        data2send = 'hBC;
      end
    end else begin
	  data2sendF = 'hBC;
      out44 = 8;
      data_outS = 0;
      data2send = data2sendF;
    end
  end

endmodule // ParaleloSerie

ParaleloSerie/bancoprueba.v
`timescale 1ns/100ps
//`include "gen.v"
`include "probador.v"
`include "ParaleloSerie.v"
`include "ParaleloSerie_Est.v"
`include "cmos_cells.v"
//`include "Generador128f.v"
module bancoprueba;

    wire clk_f;
    wire clk_8f;
    wire valid_in;
    wire [7:0]data_inP;
    wire [7:0] data2send;
    wire  data_outS;
    wire [7:0] data2send_est;
    wire data_outS_est;
    wire reset;


ParaleloSerie ParaleloSerie (/*AUTOINST*/
			     // Outputs
			     .data2send		(data2send[7:0]),
			     .data_outS		(data_outS),
			     // Inputs
			     .data_inP		(data_inP[7:0]),
			     .reset		(reset),
			     .clk_8f		(clk_8f),
			     .clk_f		(clk_f),
			     .valid_in		(valid_in));
probador prob (/*AUTOINST*/
	       // Outputs
	       .clk_8f			(clk_8f),
	       .valid_in		(valid_in),
	       .data_inP		(data_inP[7:0]),
	       .reset			(reset),
	       .clk_f			(clk_f),
	       // Inputs
	       .data2send		(data2send[7:0]),
	       .data_outS		(data_outS));
ParaleloSerie_Est ParaleloSerie_Est_(/*AUTOINST*/
				     // Outputs
				     .data2send_est	(data2send_est[7:0]),
				     .data_outS_est	(data_outS_est),
				     // Inputs
				     .clk_8f		(clk_8f),
				     .clk_f		(clk_f),
				     .data_inP		(data_inP[7:0]),
				     .reset		(reset),
				     .valid_in		(valid_in));


endmodule

ParaleloSerie/ParaleloSerie.vcd
$date
	Wed May 15 15:18:13 2019
$end
$version
	Icarus Verilog
$end
$timescale
	100ps
$end
$scope module bancoprueba $end
$var wire 1 ! valid_in $end
$var wire 1 " reset $end
$var wire 1 # data_outS_est $end
$var wire 1 $ data_outS $end
$var wire 8 % data_inP [7:0] $end
$var wire 8 & data2send_est [7:0] $end
$var wire 8 ' data2send [7:0] $end
$var wire 1 ( clk_f $end
$var wire 1 ) clk_8f $end
$scope module ParaleloSerie $end
$var wire 1 ! valid_in $end
$var wire 1 " reset $end
$var wire 8 * data_inP [7:0] $end
$var wire 1 ( clk_f $end
$var wire 1 ) clk_8f $end
$var reg 8 + data2send [7:0] $end
$var reg 8 , data2sendF [7:0] $end
$var reg 1 $ data_outS $end
$var reg 3 - out44 [2:0] $end
$var reg 3 . out44F [2:0] $end
$upscope $end
$scope module ParaleloSerie_Est_ $end
$var wire 1 / _07_ $end
$var wire 1 ! valid_in $end
$var wire 1 " reset $end
$var wire 3 0 out44_est [2:0] $end
$var wire 1 # data_outS_est $end
$var wire 8 1 data_inP [7:0] $end
$var wire 8 2 data2send_est [7:0] $end
$var wire 1 ( clk_f $end
$var wire 1 ) clk_8f $end
$var wire 32 3 _06_ [31:0] $end
$var wire 32 4 _05_ [31:0] $end
$var wire 8 5 _04_ [7:0] $end
$var wire 8 6 _03_ [7:0] $end
$var wire 8 7 _02_ [7:0] $end
$var wire 8 8 _01_ [7:0] $end
$var wire 3 9 _00_ [2:0] $end
$var reg 8 : data2send_estF [7:0] $end
$var reg 3 ; out44_estF [2:0] $end
$upscope $end
$scope module prob $end
$var wire 8 < data2send [7:0] $end
$var wire 1 $ data_outS $end
$var reg 1 ) clk_8f $end
$var reg 1 ( clk_f $end
$var reg 8 = data_inP [7:0] $end
$var reg 1 " reset $end
$var reg 1 ! valid_in $end
$upscope $end
$upscope $end
$enddefinitions $end
#0
$dumpvars
bx =
bx <
b111 ;
bx :
b111 9
bx 8
bzx 7
bzxxxx 6
bzxx 5
bz0z 4
bz11z 3
bx 2
bx 1
b0 0
0/
b111 .
b0 -
bx ,
bx +
bx *
1)
0(
bx '
bx &
bx %
0$
0#
0"
x!
$end
#10
0)
#20
1)
#30
0)
#40
1)
#50
0)
#60
1)
#70
0)
#80
bz1 7
bz10 5
bz1011 6
b10111100 &
b10111100 2
b10111100 8
0!
bz00z 3
bz1z 4
b110 9
0/
b111 0
1#
b10111100 '
b10111100 +
b10111100 <
b111 -
1$
1"
1)
1(
#90
0)
#100
b101 9
0#
b110 0
bz0 7
b110 -
0$
b10111100 :
b110 ;
b10111100 ,
b110 .
1)
#110
0)
#120
1/
b100 9
1#
bz01z 3
bz1z 4
bz1 7
b101 0
bz11 5
b101 -
1$
b101 .
b101 ;
1)
#130
0)
#140
bz0z 4
b11 9
0/
b100 0
b100 -
b100 ;
b100 .
1)
#150
0)
#160
b10 9
0/
bz1z 4
bz10z 3
bz11 5
b11 0
bz1100 6
b11 -
b11 .
b11 ;
1)
0(
#170
0)
#180
b1 9
b10 0
b10 -
b10 ;
b10 .
1)
#190
0)
#200
1/
0#
b0 9
bz11z 3
bz1z 4
bz0 7
b1 0
bz00 5
b1 -
0$
b1 .
b1 ;
1)
#210
0)
#220
bz0z 4
b111 9
0/
b0 0
b0 -
b0 ;
b0 .
1)
#230
0)
#240
1#
b110 9
0/
bz1z 4
bz1 7
bz00z 3
b10101010 &
b10101010 2
bz10 5
b111 0
bz1010 6
b10101010 8
b10101010 '
b10101010 +
b10101010 <
b111 -
1$
b111 .
b111 ;
b10101010 %
b10101010 *
b10101010 1
b10101010 =
1!
1)
1(
#250
0)
#260
b101 9
0#
b110 0
bz0 7
b110 -
0$
b10101010 :
b110 ;
b10101010 ,
b110 .
1)
#270
0)
#280
1/
b100 9
1#
bz01z 3
bz1z 4
bz1 7
b101 0
b101 -
1$
b101 .
b101 ;
1)
#290
0)
#300
bz0z 4
b11 9
0/
0#
b100 0
bz0 7
b100 -
0$
b100 ;
b100 .
1)
#310
0)
#320
b10 9
0/
1#
bz1z 4
bz10z 3
bz1 7
b11 0
b11 -
1$
b11 .
b11 ;
1)
0(
#330
0)
#340
b1 9
0#
b10 0
bz0 7
b10 -
0$
b10 ;
b10 .
1)
#350
0)
#360
1/
b0 9
1#
bz11z 3
bz1z 4
bz1 7
b1 0
b1 -
1$
b1 .
b1 ;
1)
#370
0)
#380
bz0z 4
b111 9
0/
0#
b0 0
bz0 7
b0 -
0$
b0 ;
b0 .
1)
#390
0)
#400
bz1011 6
b110 9
0/
1#
bz1z 4
bz00z 3
b10111011 &
b10111011 2
bz1 7
b111 0
b10111011 8
b10111011 '
b10111011 +
b10111011 <
b111 -
1$
b111 .
b111 ;
b10111011 %
b10111011 *
b10111011 1
b10111011 =
1)
1(
#410
0)
#420
b101 9
0#
b110 0
bz0 7
b110 -
0$
b10111011 :
b110 ;
b10111011 ,
b110 .
1)
#430
0)
#440
1/
b100 9
1#
bz01z 3
bz1z 4
bz1 7
b101 0
bz11 5
b101 -
1$
b101 .
b101 ;
1)
#450
0)
#460
bz0z 4
b11 9
0/
b100 0
b100 -
b100 ;
b100 .
1)
#470
0)
#480
b10 9
0/
bz1z 4
bz10z 3
bz10 5
b11 0
b11 -
b11 .
b11 ;
1)
0(
#490
0)
#500
b1 9
0#
b10 0
bz0 7
b10 -
0$
b10 ;
b10 .
1)
#510
0)
#520
1/
b0 9
1#
bz11z 3
bz1z 4
bz1 7
b1 0
bz11 5
b1 -
1$
b1 .
b1 ;
1)
#530
0)
#540
bz0z 4
b111 9
0/
b0 0
b0 -
b0 ;
b0 .
1)
#550
0)
#560
bz1010 6
b110 9
0/
bz1z 4
bz00z 3
b10101100 &
b10101100 2
bz10 5
b111 0
b10101100 8
b10101100 '
b10101100 +
b10101100 <
b111 -
b111 .
b111 ;
b10101100 %
b10101100 *
b10101100 1
b10101100 =
1)
1(
#570
0)
#580
b101 9
0#
b110 0
bz0 7
b110 -
0$
b10101100 :
b110 ;
b10101100 ,
b110 .
1)
#590
0)
#600
1/
b100 9
1#
bz01z 3
bz1z 4
bz1 7
b101 0
b101 -
1$
b101 .
b101 ;
1)
#610
0)
#620
bz0z 4
b11 9
0/
0#
b100 0
bz0 7
b100 -
0$
b100 ;
b100 .
1)
#630
0)
#640
b10 9
0/
1#
bz1z 4
bz10z 3
bz11 5
bz1 7
b11 0
bz1100 6
b11 -
1$
b11 .
b11 ;
1)
0(
#650
0)
#660
b1 9
b10 0
b10 -
b10 ;
b10 .
1)
#670
0)
#680
1/
0#
b0 9
bz11z 3
bz1z 4
bz0 7
b1 0
bz00 5
b1 -
0$
b1 .
b1 ;
1)
#690
0)
#700
bz0z 4
b111 9
0/
b0 0
b0 -
b0 ;
b0 .
1)
#710
0)
#720
1#
b110 9
0/
bz1z 4
bz1 7
bz00z 3
bz10 5
b111 0
bz1010 6
b111 -
1$
b111 .
b111 ;
1)
1(
#730
0)
#740
b101 9
0#
b110 0
bz0 7
b110 -
0$
b110 ;
b110 .
1)
#750
0)
#760
1/
b100 9
1#
bz01z 3
bz1z 4
bz1 7
b101 0
b101 -
1$
b101 .
b101 ;
1)
#770
0)
#780
bz0z 4
b11 9
0/
0#
b100 0
bz0 7
b100 -
0$
b100 ;
b100 .
1)
#790
0)
#800
b10 9
0/
1#
bz1z 4
bz10z 3
bz11 5
bz1 7
b11 0
bz1100 6
b11 -
1$
b11 .
b11 ;
1)
0(
#810
0)
#820
b1 9
b10 0
b10 -
b10 ;
b10 .
1)
#830
0)
#840
1/
0#
b0 9
bz11z 3
bz1z 4
bz0 7
b1 0
bz00 5
b1 -
0$
b1 .
b1 ;
1)
#850
0)
#860
bz0z 4
b111 9
0/
b0 0
b0 -
b0 ;
b0 .
1)
#870
0)
#880
1#
b110 9
0/
bz1z 4
bz1 7
bz00z 3
bz10 5
b111 0
bz1010 6
b111 -
1$
b111 .
b111 ;
1)
1(
#890
0)
#900
b101 9
0#
b110 0
bz0 7
b110 -
0$
b110 ;
b110 .
1)
#910
0)
#920
1/
b100 9
1#
bz01z 3
bz1z 4
bz1 7
b101 0
b101 -
1$
b101 .
b101 ;
1)
#930
0)
#940
bz0z 4
b11 9
0/
0#
b100 0
bz0 7
b100 -
0$
b100 ;
b100 .
1)
#950
0)
#960
b10 9
0/
1#
bz1z 4
bz10z 3
bz11 5
bz1 7
b11 0
bz1100 6
b11 -
1$
b11 .
b11 ;
1)
0(
#970
0)
#980
b1 9
b10 0
b10 -
b10 ;
b10 .
1)
#990
0)
#1000
1/
0#
b0 9
bz11z 3
bz1z 4
bz0 7
b1 0
bz00 5
b1 -
0$
b1 .
b1 ;
1)
#1010
0)
#1020
bz0z 4
b111 9
0/
b0 0
b0 -
b0 ;
b0 .
1)
#1030
0)
#1040
1#
b110 9
0/
bz1z 4
bz1 7
bz00z 3
bz10 5
b111 0
bz1010 6
b111 -
1$
b111 .
b111 ;
1)
1(
#1050
0)
#1060
b101 9
0#
b110 0
bz0 7
b110 -
0$
b110 ;
b110 .
1)
#1070
0)
#1080
1/
b100 9
1#
bz01z 3
bz1z 4
bz1 7
b101 0
b101 -
1$
b101 .
b101 ;
1)
#1090
0)
#1100
bz0z 4
b11 9
0/
0#
b100 0
bz0 7
b100 -
0$
b100 ;
b100 .
1)
#1110
0)
#1120
b10 9
0/
1#
bz1z 4
bz10z 3
bz11 5
bz1 7
b11 0
bz1100 6
b11 -
1$
b11 .
b11 ;
1)
0(
#1130
0)
#1140
b1 9
b10 0
b10 -
b10 ;
b10 .
1)
#1150
0)
#1160
1/
0#
b0 9
bz11z 3
bz1z 4
bz0 7
b1 0
bz00 5
b1 -
0$
b1 .
b1 ;
1)
#1170
0)
#1180
bz0z 4
b111 9
0/
b0 0
b0 -
b0 ;
b0 .
1)
#1190
0)
#1200
1#
b110 9
0/
bz1z 4
bz1 7
bz00z 3
bz10 5
b111 0
bz1010 6
b111 -
1$
b111 .
b111 ;
1)
1(
#1210
0)
#1220
b101 9
0#
b110 0
bz0 7
b110 -
0$
b110 ;
b110 .
1)
#1230
0)
#1240
1/
b100 9
1#
bz01z 3
bz1z 4
bz1 7
b101 0
b101 -
1$
b101 .
b101 ;
1)
#1250
0)
#1260
bz0z 4
b11 9
0/
0#
b100 0
bz0 7
b100 -
0$
b100 ;
b100 .
1)
#1270
0)
#1280
b10 9
0/
1#
bz1z 4
bz10z 3
bz11 5
bz1 7
b11 0
bz1100 6
b11 -
1$
b11 .
b11 ;
1)
0(
#1290
0)
#1300
b1 9
b10 0
b10 -
b10 ;
b10 .
1)
#1310
0)
#1320
1/
0#
b0 9
bz11z 3
bz1z 4
bz0 7
b1 0
bz00 5
b1 -
0$
b1 .
b1 ;
1)
#1330
0)
#1340
bz0z 4
b111 9
0/
b0 0
b0 -
b0 ;
b0 .
1)
#1350
0)
#1360
1#
b110 9
0/
bz1z 4
bz1 7
bz00z 3
bz10 5
b111 0
bz1010 6
b111 -
1$
b111 .
b111 ;
1)
1(
#1370
0)
#1380
b101 9
0#
b110 0
bz0 7
b110 -
0$
b110 ;
b110 .
1)
#1390
0)
#1400
1/
b100 9
1#
bz01z 3
bz1z 4
bz1 7
b101 0
b101 -
1$
b101 .
b101 ;
1)
#1410
0)
#1420
bz0z 4
b11 9
0/
0#
b100 0
bz0 7
b100 -
0$
b100 ;
b100 .
1)
#1430
0)
#1440
b10 9
0/
1#
bz1z 4
bz10z 3
bz11 5
bz1 7
b11 0
bz1100 6
b11 -
1$
b11 .
b11 ;
1)
0(
#1450
0)
#1460
b1 9
b10 0
b10 -
b10 ;
b10 .
1)
#1470
0)
#1480
1/
0#
b0 9
bz11z 3
bz1z 4
bz0 7
b1 0
bz00 5
b1 -
0$
b1 .
b1 ;
1)
#1490
0)
#1500
bz0z 4
b111 9
0/
b0 0
b0 -
b0 ;
b0 .
1)
#1510
0)
#1520
1#
b110 9
0/
bz1z 4
bz1 7
bz00z 3
bz10 5
b111 0
bz1010 6
b111 -
1$
b111 .
b111 ;
1)
1(
#1530
0)
#1540
b101 9
0#
b110 0
bz0 7
b110 -
0$
b110 ;
b110 .
1)
#1550
0)
#1560
1/
b100 9
1#
bz01z 3
bz1z 4
bz1 7
b101 0
b101 -
1$
b101 .
b101 ;
1)
